quantumics/__init__.py
quantumics/core.py
quantumics/statespaces.py
quantumics/qchemistry/__init__.py
quantumics/qclouds/__init__.py
quantumics/qclouds/qserver.py
quantumics/qdatabases/__init__.py
quantumics/qdatabases/core.py
quantumics/qhilbertspaces/__init__.py
quantumics/qhilbertspaces/qhilbertspaces.py
quantumics/qmaps/__init__.py
quantumics/qmaps/core.py
quantumics/qmaterials/__init__.py
quantumics/qmodels/__init__.py
quantumics/qmodels/qmodels.py
quantumics/qnanotech/__init__.py
quantumics/qnanotech/nanotech.py
quantumics/qnumpy/__init__.py
quantumics/qnumpy/qnumpy.py
quantumics/qoperators/__init__.py
quantumics/qoperators/qoperators.py
quantumics/qpandas/__init__.py
quantumics/qpandas/qpandas.py
quantumics/qphysics/__init__.py
quantumics/qprocessors/__init__.py
quantumics/qprocessors/qprocessors.py
quantumics/qsklearn/__init__.py
quantumics/qviews/__init__.py
quantumics-0.0.3.dist-info/METADATA
quantumics-0.0.3.dist-info/WHEEL
quantumics-0.0.3.dist-info/entry_points.txt
quantumics-0.0.3.dist-info/top_level.txt
quantumics-0.0.3.dist-info/RECORD
