Metadata-Version: 2.1
Name: quantumics
Version: 0.0.3
Summary: Library for processor agnostic quantum-classical data science and artificial intelligence
Home-page: https://gitlab.com/quantumics/quantumics
Author: Jawad Bashorun
Author-email: jaybashorun@gmail.com
License: MIT
Platform: UNKNOWN
Classifier: License :: OSI Approved :: MIT License
Classifier: Programming Language :: Python :: 3
Classifier: Programming Language :: Python :: 3.7
Requires-Dist: numpy
Requires-Dist: qiskit
Requires-Dist: dwave-ocean-sdk
Requires-Dist: theano
Requires-Dist: pandas
Requires-Dist: sklearn
Requires-Dist: mongo
